idatanlp/__init__.py
idatanlp/ie/__init__.py
idatanlp/ie/doccano.py
idatanlp/ie/evaluate.py
idatanlp/ie/finetune.py
idatanlp/ie/model.py
idatanlp/ie/utils.py
idatanlp/tools/__init__.py
idatanlp/tools/converter.py
idatanlp/tools/tools.py
idata_nlp-0.1.0.dist-info/METADATA
idata_nlp-0.1.0.dist-info/WHEEL
idata_nlp-0.1.0.dist-info/top_level.txt
idata_nlp-0.1.0.dist-info/RECORD
